declic.py
declic-1.0.2.dist-info/DESCRIPTION.rst
declic-1.0.2.dist-info/METADATA
declic-1.0.2.dist-info/RECORD
declic-1.0.2.dist-info/WHEEL
declic-1.0.2.dist-info/metadata.json
declic-1.0.2.dist-info/top_level.txt
