Metadata-Version: 2.0
Name: declic
Version: 1.0.2
Summary: Declic (DEcorator-oriented CLI Creator) is a tiny Python 3 package for creating command line interfaces
Home-page: https://github.com/Septaris/declic
Author: S. Lion
Author-email: sonny.lion@laposte.net
License: MIT
Platform: UNKNOWN
